[
  {
    "text": "",
    "url": "https://www.bing.com/?FORM=Z9FD1"
  },
  {
    "text": "Privacy Policy",
    "url": "https://www.bing.com/images?FORM=SBIRDI"
  },
  {
    "text": "Terms of Use",
    "url": "https://www.bing.com/images?FORM=SBIRDI"
  },
  {
    "text": "",
    "url": "https://www.bing.com/images"
  },
  {
    "text": "",
    "url": "javascript:void(0)"
  },
  {
    "text": "",
    "url": "https://www.bing.com/rebates/payouts"
  },
  {
    "text": "",
    "url": "javascript:void(0)"
  },
  {
    "text": "",
    "url": "javascript:void(0)"
  },
  {
    "text": "All",
    "url": "https://www.bing.com/search?q=Bing+AI&FORM=HDRSC1"
  },
  {
    "text": "Search",
    "url": "https://www.bing.com/copilotsearch?q=&FORM=CSSCOP"
  },
  {
    "text": "Images",
    "url": "https://www.bing.com/images?FORM=HDRSC2"
  },
  {
    "text": "Create",
    "url": "https://www.bing.com/images/create/ai-image-generator?FORM=IRPGEN"
  },
  {
    "text": "Inspiration",
    "url": "https://www.bing.com/inspire?FORM=IRPFED"
  },
  {
    "text": "Collections",
    "url": "https://www.bing.com/saves?FORM=IRPCOL"
  },
  {
    "text": "",
    "url": "javascript:void(0)"
  },
  {
    "text": "Videos",
    "url": "https://www.bing.com/videos/search?q=&FORM=HDRSC3"
  },
  {
    "text": "Maps",
    "url": "https://www.bing.com/maps?q=&FORM=HDRSC4"
  },
  {
    "text": "News",
    "url": "https://www.bing.com/news/search?q=&FORM=HDRSC6"
  },
  {
    "text": "More",
    "url": "javascript:void(0);"
  },
  {
    "text": "Shopping",
    "url": "https://www.bing.com/shop/topics?q=&FORM=SHOPTB"
  },
  {
    "text": "Flights",
    "url": "https://www.bing.com/travel/search?q=&m=flights&FORM=FBSCOP"
  },
  {
    "text": "Travel",
    "url": "https://www.bing.com/travel/search?q=&m=travel&FORM=THSCOP"
  },
  {
    "text": "Notebook",
    "url": "javascript:void(0)"
  },
  {
    "text": "",
    "url": "https://www.bing.com/images/search?view=detailV2&ccid=c%2bUO39B%2f&id=61D7FD8E4893A02837A81003A33F46C494E7FAC8&thid=OIP.c-UO39B_P8HqpTkELqF6zgHaLH&mediaurl=http%3a%2f%2fpm1.aminoapps.com%2f7586%2f1a5e7ea6843e14502202fb764e2360a9560189f5r1-750-1125v2_uhq.jpg&exph=2048&expw=1364&FORM=IRPFED&ck=9A4D6CD65486D864A2099A139628EFE8&reqid=884BD56324234530B8388CCCFF048294&selectedIndex=0&itb=0&idpp=insfeed"
  },
  {
    "text": "aminoapps.com",
    "url": "https://aminoapps.com/c/mermaid-amino/page/blog/the-3-tails/G5DJ_jxeHnuz8JYWeL6vK6zG4VZRojP0nng"
  },
  {
    "text": "",
    "url": "https://www.bing.com/images/search?view=detailV2&ccid=c%2bUO39B%2f&id=61D7FD8E4893A02837A81003A33F46C494E7FAC8&thid=OIP.c-UO39B_P8HqpTkELqF6zgHaLH&mediaurl=http%3a%2f%2fpm1.aminoapps.com%2f7586%2f1a5e7ea6843e14502202fb764e2360a9560189f5r1-750-1125v2_uhq.jpg&exph=2048&expw=1364&FORM=IRPFED&ck=9A4D6CD65486D864A2099A139628EFE8&reqid=884BD56324234530B8388CCCFF048294&selectedIndex=0&itb=0&idpp=insfeed"
  },
  {
    "text": "The 3 Tails | Mermaid Amino Amino",
    "url": "https://www.bing.com/images/search?view=detailV2&ccid=c%2bUO39B%2f&id=61D7FD8E4893A02837A81003A33F46C494E7FAC8&thid=OIP.c-UO39B_P8HqpTkELqF6zgHaLH&mediaurl=http%3a%2f%2fpm1.aminoapps.com%2f7586%2f1a5e7ea6843e14502202fb764e2360a9560189f5r1-750-1125v2_uhq.jpg&exph=2048&expw=1364&FORM=IRPFED&ck=9A4D6CD65486D864A2099A139628EFE8&reqid=884BD56324234530B8388CCCFF048294&selectedIndex=0&itb=0&idpp=insfeed"
  },
  {
    "text": "",
    "url": "https://www.bing.com/images?FORM=SBIRDI#CA!Like"
  },
  {
    "text": "",
    "url": "https://www.bing.com/images?FORM=SBIRDI#CA!Unlike"
  },
  {
    "text": "",
    "url": "https://www.bing.com/images?FORM=SBIRDI#CA!dtmnu"
  },
  {
    "text": "",
    "url": "https://www.bing.com/images/search?view=detailV2&ccid=mzXsuIgu&id=B1A065AEDF5D12EC9F1EBA9B78138526BE75CCD6&thid=OIP.mzXsuIguYLa3oSmExyAevAHaLH&mediaurl=https%3a%2f%2fcourtneysworld.co%2fwp-content%2fuploads%2f2024%2f04%2fCelestial-Moon-Phase-Wall-Hangings.png&exph=1500&expw=1000&FORM=IRPFED&ck=056CFF2B012C71B89DBCC893E0D37CCE&reqid=884BD56324234530B8388CCCFF048294&selectedIndex=3&itb=0&idpp=insfeed"
  },
  {
    "text": "courtneysworld.co",
    "url": "https://courtneysworld.co/home-decor/boho-bedroom-wall-decor-ideas/"
  },
  {
    "text": "",
    "url": "https://www.bing.com/images/search?view=detailV2&ccid=mzXsuIgu&id=B1A065AEDF5D12EC9F1EBA9B78138526BE75CCD6&thid=OIP.mzXsuIguYLa3oSmExyAevAHaLH&mediaurl=https%3a%2f%2fcourtneysworld.co%2fwp-content%2fuploads%2f2024%2f04%2fCelestial-Moon-Phase-Wall-Hangings.png&exph=1500&expw=1000&FORM=IRPFED&ck=056CFF2B012C71B89DBCC893E0D37CCE&reqid=884BD56324234530B8388CCCFF048294&selectedIndex=3&itb=0&idpp=insfeed"
  },
  {
    "text": "29 Boho Bedroom Wall Decor Ideas - Courtneys World",
    "url": "https://www.bing.com/images/search?view=detailV2&ccid=mzXsuIgu&id=B1A065AEDF5D12EC9F1EBA9B78138526BE75CCD6&thid=OIP.mzXsuIguYLa3oSmExyAevAHaLH&mediaurl=https%3a%2f%2fcourtneysworld.co%2fwp-content%2fuploads%2f2024%2f04%2fCelestial-Moon-Phase-Wall-Hangings.png&exph=1500&expw=1000&FORM=IRPFED&ck=056CFF2B012C71B89DBCC893E0D37CCE&reqid=884BD56324234530B8388CCCFF048294&selectedIndex=3&itb=0&idpp=insfeed"
  },
  {
    "text": "",
    "url": "https://www.bing.com/images?FORM=SBIRDI#CA!Like"
  },
  {
    "text": "",
    "url": "https://www.bing.com/images?FORM=SBIRDI#CA!Unlike"
  },
  {
    "text": "",
    "url": "https://www.bing.com/images?FORM=SBIRDI#CA!dtmnu"
  },
  {
    "text": "",
    "url": "https://www.bing.com/images/search?view=detailV2&ccid=3ciMygZD&id=CF853E7D938CC9EE37D4C84BDF441D64027826AC&thid=OIP.3ciMygZDJCHmeVgTwPWQPwHaJF&mediaurl=https%3a%2f%2flookaside.fbsbx.com%2flookaside%2fcrawler%2fmedia%2f%3fmedia_id%3d141888191698907&exph=1943&expw=1583&FORM=IRPFED&ck=AB14EE954EC71216845D1B7AC44B84E2&reqid=884BD56324234530B8388CCCFF048294&selectedIndex=8&itb=0&idpp=insfeed"
  },
  {
    "text": "facebook.com",
    "url": "https://www.facebook.com/104936355394091/photos/a.107568365130890/141888191698907/"
  },
  {
    "text": "",
    "url": "https://www.bing.com/images/search?view=detailV2&ccid=3ciMygZD&id=CF853E7D938CC9EE37D4C84BDF441D64027826AC&thid=OIP.3ciMygZDJCHmeVgTwPWQPwHaJF&mediaurl=https%3a%2f%2flookaside.fbsbx.com%2flookaside%2fcrawler%2fmedia%2f%3fmedia_id%3d141888191698907&exph=1943&expw=1583&FORM=IRPFED&ck=AB14EE954EC71216845D1B7AC44B84E2&reqid=884BD56324234530B8388CCCFF048294&selectedIndex=8&itb=0&idpp=insfeed"
  },
  {
    "text": "Facebook",
    "url": "https://www.bing.com/images/search?view=detailV2&ccid=3ciMygZD&id=CF853E7D938CC9EE37D4C84BDF441D64027826AC&thid=OIP.3ciMygZDJCHmeVgTwPWQPwHaJF&mediaurl=https%3a%2f%2flookaside.fbsbx.com%2flookaside%2fcrawler%2fmedia%2f%3fmedia_id%3d141888191698907&exph=1943&expw=1583&FORM=IRPFED&ck=AB14EE954EC71216845D1B7AC44B84E2&reqid=884BD56324234530B8388CCCFF048294&selectedIndex=8&itb=0&idpp=insfeed"
  },
  {
    "text": "",
    "url": "https://www.bing.com/images?FORM=SBIRDI#CA!Like"
  },
  {
    "text": "",
    "url": "https://www.bing.com/images?FORM=SBIRDI#CA!Unlike"
  },
  {
    "text": "",
    "url": "https://www.bing.com/images?FORM=SBIRDI#CA!dtmnu"
  },
  {
    "text": "",
    "url": "https://www.bing.com/images/search?view=detailV2&ccid=VSgLj5%2bj&id=FA83AB2946C4A90373AA73E5E62DB1CD42A19CB5&thid=OIP.VSgLj5-jmzgatblOZ4eVkQHaMs&mediaurl=https%3a%2f%2fmedia.licdn.com%2fdms%2fimage%2fv2%2fC4E22AQETmbQqTAYPLA%2ffeedshare-shrink_2048_1536%2ffeedshare-shrink_2048_1536%2f0%2f1637964947840%3fe%3d2147483647%26v%3dbeta%26t%3dc7WfAdJoDGHbqgU55DUEQOT2kOidb2xJUcKx8Ijx_44&exph=1028&expw=600&FORM=IRPFED&ck=5B0DE80FF7236BFF5AACCDE1B376A4BA&reqid=884BD56324234530B8388CCCFF048294&selectedIndex=9&itb=0&idpp=insfeed"
  },
  {
    "text": "linkedin.com",
    "url": "https://www.linkedin.com/posts/george-karam-946a5a211_my-artwork-activity-6870122938159439872-gqJw"
  },
  {
    "text": "",
    "url": "https://www.bing.com/images/search?view=detailV2&ccid=VSgLj5%2bj&id=FA83AB2946C4A90373AA73E5E62DB1CD42A19CB5&thid=OIP.VSgLj5-jmzgatblOZ4eVkQHaMs&mediaurl=https%3a%2f%2fmedia.licdn.com%2fdms%2fimage%2fv2%2fC4E22AQETmbQqTAYPLA%2ffeedshare-shrink_2048_1536%2ffeedshare-shrink_2048_1536%2f0%2f1637964947840%3fe%3d2147483647%26v%3dbeta%26t%3dc7WfAdJoDGHbqgU55DUEQOT2kOidb2xJUcKx8Ijx_44&exph=1028&expw=600&FORM=IRPFED&ck=5B0DE80FF7236BFF5AACCDE1B376A4BA&reqid=884BD56324234530B8388CCCFF048294&selectedIndex=9&itb=0&idpp=insfeed"
  },
  {
    "text": "George Karam on LinkedIn: My artwork",
    "url": "https://www.bing.com/images/search?view=detailV2&ccid=VSgLj5%2bj&id=FA83AB2946C4A90373AA73E5E62DB1CD42A19CB5&thid=OIP.VSgLj5-jmzgatblOZ4eVkQHaMs&mediaurl=https%3a%2f%2fmedia.licdn.com%2fdms%2fimage%2fv2%2fC4E22AQETmbQqTAYPLA%2ffeedshare-shrink_2048_1536%2ffeedshare-shrink_2048_1536%2f0%2f1637964947840%3fe%3d2147483647%26v%3dbeta%26t%3dc7WfAdJoDGHbqgU55DUEQOT2kOidb2xJUcKx8Ijx_44&exph=1028&expw=600&FORM=IRPFED&ck=5B0DE80FF7236BFF5AACCDE1B376A4BA&reqid=884BD56324234530B8388CCCFF048294&selectedIndex=9&itb=0&idpp=insfeed"
  },
  {
    "text": "",
    "url": "https://www.bing.com/images?FORM=SBIRDI#CA!Like"
  },
  {
    "text": "",
    "url": "https://www.bing.com/images?FORM=SBIRDI#CA!Unlike"
  },
  {
    "text": "",
    "url": "https://www.bing.com/images?FORM=SBIRDI#CA!dtmnu"
  },
  {
    "text": "",
    "url": "https://www.bing.com/images/search?view=detailV2&ccid=rcSL37Uv&id=F182F1A10F170A14B300A94F04150A4EE9C2CC07&thid=OIP.rcSL37Uvb6biCt_8-knnXwHaLH&mediaurl=https%3a%2f%2f64.media.tumblr.com%2f3df94cd3b08d431ce6b416404192adc3%2ftumblr_oxmma3WFHl1u8wonlo1_1280.jpg&exph=1350&expw=900&FORM=IRPFED&ck=C208C3B6A91D7AF8372C5F80E1C72253&reqid=884BD56324234530B8388CCCFF048294&selectedIndex=13&itb=0&idpp=insfeed"
  },
  {
    "text": "sssoul.tumblr.com",
    "url": "https://sssoul.tumblr.com/"
  },
  {
    "text": "",
    "url": "https://www.bing.com/images/search?view=detailV2&ccid=rcSL37Uv&id=F182F1A10F170A14B300A94F04150A4EE9C2CC07&thid=OIP.rcSL37Uvb6biCt_8-knnXwHaLH&mediaurl=https%3a%2f%2f64.media.tumblr.com%2f3df94cd3b08d431ce6b416404192adc3%2ftumblr_oxmma3WFHl1u8wonlo1_1280.jpg&exph=1350&expw=900&FORM=IRPFED&ck=C208C3B6A91D7AF8372C5F80E1C72253&reqid=884BD56324234530B8388CCCFF048294&selectedIndex=13&itb=0&idpp=insfeed"
  },
  {
    "text": "soul of nature",
    "url": "https://www.bing.com/images/search?view=detailV2&ccid=rcSL37Uv&id=F182F1A10F170A14B300A94F04150A4EE9C2CC07&thid=OIP.rcSL37Uvb6biCt_8-knnXwHaLH&mediaurl=https%3a%2f%2f64.media.tumblr.com%2f3df94cd3b08d431ce6b416404192adc3%2ftumblr_oxmma3WFHl1u8wonlo1_1280.jpg&exph=1350&expw=900&FORM=IRPFED&ck=C208C3B6A91D7AF8372C5F80E1C72253&reqid=884BD56324234530B8388CCCFF048294&selectedIndex=13&itb=0&idpp=insfeed"
  },
  {
    "text": "",
    "url": "https://www.bing.com/images?FORM=SBIRDI#CA!Like"
  },
  {
    "text": "",
    "url": "https://www.bing.com/images?FORM=SBIRDI#CA!Unlike"
  },
  {
    "text": "",
    "url": "https://www.bing.com/images?FORM=SBIRDI#CA!dtmnu"
  },
  {
    "text": "",
    "url": "https://www.bing.com/images/search?view=detailV2&ccid=CvFaIdsR&id=FD2F75675A9B5372DF7014B6014FA72D880A18A2&thid=OIP.CvFaIdsRz54j5gnz3VgqvgHaJD&mediaurl=https%3a%2f%2fi.pinimg.com%2foriginals%2f50%2ff8%2fed%2f50f8ed95921f38e8f786b47fb50cbfa0.jpg&exph=885&expw=724&FORM=IRPFED&ck=14777E1D74C0A2915026B3086112CA45&reqid=884BD56324234530B8388CCCFF048294&selectedIndex=16&itb=0&idpp=insfeed"
  },
  {
    "text": "artofit.org",
    "url": "https://www.artofit.org/image-gallery/rolls-royce-phantom-viii/"
  },
  {
    "text": "",
    "url": "https://www.bing.com/images/search?view=detailV2&ccid=CvFaIdsR&id=FD2F75675A9B5372DF7014B6014FA72D880A18A2&thid=OIP.CvFaIdsRz54j5gnz3VgqvgHaJD&mediaurl=https%3a%2f%2fi.pinimg.com%2foriginals%2f50%2ff8%2fed%2f50f8ed95921f38e8f786b47fb50cbfa0.jpg&exph=885&expw=724&FORM=IRPFED&ck=14777E1D74C0A2915026B3086112CA45&reqid=884BD56324234530B8388CCCFF048294&selectedIndex=16&itb=0&idpp=insfeed"
  },
  {
    "text": "Rolls royce phantom viii – Artofit",
    "url": "https://www.bing.com/images/search?view=detailV2&ccid=CvFaIdsR&id=FD2F75675A9B5372DF7014B6014FA72D880A18A2&thid=OIP.CvFaIdsRz54j5gnz3VgqvgHaJD&mediaurl=https%3a%2f%2fi.pinimg.com%2foriginals%2f50%2ff8%2fed%2f50f8ed95921f38e8f786b47fb50cbfa0.jpg&exph=885&expw=724&FORM=IRPFED&ck=14777E1D74C0A2915026B3086112CA45&reqid=884BD56324234530B8388CCCFF048294&selectedIndex=16&itb=0&idpp=insfeed"
  },
  {
    "text": "",
    "url": "https://www.bing.com/images?FORM=SBIRDI#CA!Like"
  },
  {
    "text": "",
    "url": "https://www.bing.com/images?FORM=SBIRDI#CA!Unlike"
  },
  {
    "text": "",
    "url": "https://www.bing.com/images?FORM=SBIRDI#CA!dtmnu"
  },
  {
    "text": "",
    "url": "https://www.bing.com/images/search?view=detailV2&ccid=eYDlAG2e&id=7D617D3765DB8BD8576E0E263B01BBAB02D5409E&thid=OIP.eYDlAG2ewXsX0Huuo-AfHgHaNK&mediaurl=https%3a%2f%2flookaside.fbsbx.com%2flookaside%2fcrawler%2fmedia%2f%3fmedia_id%3d100066628083724&exph=896&expw=504&FORM=IRPFED&ck=9DD17CAEAC2F241E8E7DE941D89772B1&reqid=884BD56324234530B8388CCCFF048294&selectedIndex=19&itb=0&idpp=insfeed"
  },
  {
    "text": "facebook.com",
    "url": "https://www.facebook.com/africahhope/"
  },
  {
    "text": "",
    "url": "https://www.bing.com/images/search?view=detailV2&ccid=eYDlAG2e&id=7D617D3765DB8BD8576E0E263B01BBAB02D5409E&thid=OIP.eYDlAG2ewXsX0Huuo-AfHgHaNK&mediaurl=https%3a%2f%2flookaside.fbsbx.com%2flookaside%2fcrawler%2fmedia%2f%3fmedia_id%3d100066628083724&exph=896&expw=504&FORM=IRPFED&ck=9DD17CAEAC2F241E8E7DE941D89772B1&reqid=884BD56324234530B8388CCCFF048294&selectedIndex=19&itb=0&idpp=insfeed"
  },
  {
    "text": "African teens proudly future leaders",
    "url": "https://www.bing.com/images/search?view=detailV2&ccid=eYDlAG2e&id=7D617D3765DB8BD8576E0E263B01BBAB02D5409E&thid=OIP.eYDlAG2ewXsX0Huuo-AfHgHaNK&mediaurl=https%3a%2f%2flookaside.fbsbx.com%2flookaside%2fcrawler%2fmedia%2f%3fmedia_id%3d100066628083724&exph=896&expw=504&FORM=IRPFED&ck=9DD17CAEAC2F241E8E7DE941D89772B1&reqid=884BD56324234530B8388CCCFF048294&selectedIndex=19&itb=0&idpp=insfeed"
  },
  {
    "text": "",
    "url": "https://www.bing.com/images?FORM=SBIRDI#CA!Like"
  },
  {
    "text": "",
    "url": "https://www.bing.com/images?FORM=SBIRDI#CA!Unlike"
  },
  {
    "text": "",
    "url": "https://www.bing.com/images?FORM=SBIRDI#CA!dtmnu"
  },
  {
    "text": "",
    "url": "https://www.bing.com/images/search?view=detailV2&ccid=7XqtwCLe&id=317156BB736265C12911D7443B42B646B623DDCB&thid=OIP.7XqtwCLeRm5bFi74x9R96wHaLH&mediaurl=https%3a%2f%2flookaside.fbsbx.com%2flookaside%2fcrawler%2fmedia%2f%3fmedia_id%3d118073574523716&exph=1104&expw=736&FORM=IRPFED&ck=1836E57CE6DCF919DD7E9B8836D4B997&reqid=884BD56324234530B8388CCCFF048294&selectedIndex=23&itb=0&idpp=insfeed"
  },
  {
    "text": "facebook.com",
    "url": "https://www.facebook.com/CachorrosFantasticos/"
  },
  {
    "text": "",
    "url": "https://www.bing.com/images/search?view=detailV2&ccid=7XqtwCLe&id=317156BB736265C12911D7443B42B646B623DDCB&thid=OIP.7XqtwCLeRm5bFi74x9R96wHaLH&mediaurl=https%3a%2f%2flookaside.fbsbx.com%2flookaside%2fcrawler%2fmedia%2f%3fmedia_id%3d118073574523716&exph=1104&expw=736&FORM=IRPFED&ck=1836E57CE6DCF919DD7E9B8836D4B997&reqid=884BD56324234530B8388CCCFF048294&selectedIndex=23&itb=0&idpp=insfeed"
  },
  {
    "text": "Cachorros Fantásticos",
    "url": "https://www.bing.com/images/search?view=detailV2&ccid=7XqtwCLe&id=317156BB736265C12911D7443B42B646B623DDCB&thid=OIP.7XqtwCLeRm5bFi74x9R96wHaLH&mediaurl=https%3a%2f%2flookaside.fbsbx.com%2flookaside%2fcrawler%2fmedia%2f%3fmedia_id%3d118073574523716&exph=1104&expw=736&FORM=IRPFED&ck=1836E57CE6DCF919DD7E9B8836D4B997&reqid=884BD56324234530B8388CCCFF048294&selectedIndex=23&itb=0&idpp=insfeed"
  },
  {
    "text": "",
    "url": "https://www.bing.com/images?FORM=SBIRDI#CA!Like"
  },
  {
    "text": "",
    "url": "https://www.bing.com/images?FORM=SBIRDI#CA!Unlike"
  },
  {
    "text": "",
    "url": "https://www.bing.com/images?FORM=SBIRDI#CA!dtmnu"
  },
  {
    "text": "",
    "url": "https://www.bing.com/images/search?view=detailV2&ccid=1Zni4XVq&id=BC4909A2AF11A570FB2E78EE091296E38021E5A0&thid=OIP.1Zni4XVqu8QPmv79oTJTvQHaNK&mediaurl=https%3a%2f%2fi.pinimg.com%2foriginals%2fc7%2fba%2f9b%2fc7ba9b751a9d3f8385cf132b9fe45db5.jpg&exph=1625&expw=914&FORM=IRPFED&ck=0CCB4C9FA936D6493A5A80F7F07949C2&reqid=884BD56324234530B8388CCCFF048294&selectedIndex=26&itb=0&idpp=insfeed"
  },
  {
    "text": "artofit.org",
    "url": "https://www.artofit.org/image-gallery/545498573626845782/fantastical-flitherings/"
  },
  {
    "text": "",
    "url": "https://www.bing.com/images/search?view=detailV2&ccid=1Zni4XVq&id=BC4909A2AF11A570FB2E78EE091296E38021E5A0&thid=OIP.1Zni4XVqu8QPmv79oTJTvQHaNK&mediaurl=https%3a%2f%2fi.pinimg.com%2foriginals%2fc7%2fba%2f9b%2fc7ba9b751a9d3f8385cf132b9fe45db5.jpg&exph=1625&expw=914&FORM=IRPFED&ck=0CCB4C9FA936D6493A5A80F7F07949C2&reqid=884BD56324234530B8388CCCFF048294&selectedIndex=26&itb=0&idpp=insfeed"
  },
  {
    "text": "Fantastical flitherings – Artofit",
    "url": "https://www.bing.com/images/search?view=detailV2&ccid=1Zni4XVq&id=BC4909A2AF11A570FB2E78EE091296E38021E5A0&thid=OIP.1Zni4XVqu8QPmv79oTJTvQHaNK&mediaurl=https%3a%2f%2fi.pinimg.com%2foriginals%2fc7%2fba%2f9b%2fc7ba9b751a9d3f8385cf132b9fe45db5.jpg&exph=1625&expw=914&FORM=IRPFED&ck=0CCB4C9FA936D6493A5A80F7F07949C2&reqid=884BD56324234530B8388CCCFF048294&selectedIndex=26&itb=0&idpp=insfeed"
  },
  {
    "text": "",
    "url": "https://www.bing.com/images?FORM=SBIRDI#CA!Like"
  },
  {
    "text": "",
    "url": "https://www.bing.com/images?FORM=SBIRDI#CA!Unlike"
  },
  {
    "text": "",
    "url": "https://www.bing.com/images?FORM=SBIRDI#CA!dtmnu"
  },
  {
    "text": "",
    "url": "https://www.bing.com/images/search?view=detailV2&ccid=vV3FMNRW&id=81AEE8CBB16898E5750F5B69768550694DCED4C2&thid=OIP.vV3FMNRWh-cBaOjHTtkVNAHaLF&mediaurl=https%3a%2f%2fi.pinimg.com%2foriginals%2fb6%2fb9%2fb8%2fb6b9b841eafe1d1ba8275f99bea88ac4.jpg&exph=844&expw=564&FORM=IRPFED&ck=67898FACE555902A0176C27FF48B4BE5&reqid=884BD56324234530B8388CCCFF048294&selectedIndex=29&itb=0&idpp=insfeed"
  },
  {
    "text": "artofit.org",
    "url": "https://www.artofit.org/image-gallery/224054150187008424/"
  },
  {
    "text": "",
    "url": "https://www.bing.com/images/search?view=detailV2&ccid=vV3FMNRW&id=81AEE8CBB16898E5750F5B69768550694DCED4C2&thid=OIP.vV3FMNRWh-cBaOjHTtkVNAHaLF&mediaurl=https%3a%2f%2fi.pinimg.com%2foriginals%2fb6%2fb9%2fb8%2fb6b9b841eafe1d1ba8275f99bea88ac4.jpg&exph=844&expw=564&FORM=IRPFED&ck=67898FACE555902A0176C27FF48B4BE5&reqid=884BD56324234530B8388CCCFF048294&selectedIndex=29&itb=0&idpp=insfeed"
  },
  {
    "text": "Artofit",
    "url": "https://www.bing.com/images/search?view=detailV2&ccid=vV3FMNRW&id=81AEE8CBB16898E5750F5B69768550694DCED4C2&thid=OIP.vV3FMNRWh-cBaOjHTtkVNAHaLF&mediaurl=https%3a%2f%2fi.pinimg.com%2foriginals%2fb6%2fb9%2fb8%2fb6b9b841eafe1d1ba8275f99bea88ac4.jpg&exph=844&expw=564&FORM=IRPFED&ck=67898FACE555902A0176C27FF48B4BE5&reqid=884BD56324234530B8388CCCFF048294&selectedIndex=29&itb=0&idpp=insfeed"
  },
  {
    "text": "",
    "url": "https://www.bing.com/images?FORM=SBIRDI#CA!Like"
  },
  {
    "text": "",
    "url": "https://www.bing.com/images?FORM=SBIRDI#CA!Unlike"
  },
  {
    "text": "",
    "url": "https://www.bing.com/images?FORM=SBIRDI#CA!dtmnu"
  },
  {
    "text": "",
    "url": "https://www.bing.com/images/search?view=detailV2&ccid=fV0PAqX4&id=D292E9FD636D52EC06666103F32C0018EC478A8B&thid=OIP.fV0PAqX4dNl79_yvEbbpBQAAAA&mediaurl=https%3a%2f%2fi.pinimg.com%2foriginals%2f8f%2ff8%2f79%2f8ff879b653bba3783e17793e34bb2061.jpg&exph=845&expw=474&FORM=IRPFED&ck=4543C52419BBFE735F9C1A7894C54B96&reqid=884BD56324234530B8388CCCFF048294&selectedIndex=32&itb=0&idpp=insfeed"
  },
  {
    "text": "bing.com",
    "url": "https://www.bing.com/images/feed?itemId=50ABBABCF86C1C0C5FA9194A78CD1FD5&ep=IDP"
  },
  {
    "text": "",
    "url": "https://www.bing.com/images/search?view=detailV2&ccid=fV0PAqX4&id=D292E9FD636D52EC06666103F32C0018EC478A8B&thid=OIP.fV0PAqX4dNl79_yvEbbpBQAAAA&mediaurl=https%3a%2f%2fi.pinimg.com%2foriginals%2f8f%2ff8%2f79%2f8ff879b653bba3783e17793e34bb2061.jpg&exph=845&expw=474&FORM=IRPFED&ck=4543C52419BBFE735F9C1A7894C54B96&reqid=884BD56324234530B8388CCCFF048294&selectedIndex=32&itb=0&idpp=insfeed"
  },
  {
    "text": "Bing Images",
    "url": "https://www.bing.com/images/search?view=detailV2&ccid=fV0PAqX4&id=D292E9FD636D52EC06666103F32C0018EC478A8B&thid=OIP.fV0PAqX4dNl79_yvEbbpBQAAAA&mediaurl=https%3a%2f%2fi.pinimg.com%2foriginals%2f8f%2ff8%2f79%2f8ff879b653bba3783e17793e34bb2061.jpg&exph=845&expw=474&FORM=IRPFED&ck=4543C52419BBFE735F9C1A7894C54B96&reqid=884BD56324234530B8388CCCFF048294&selectedIndex=32&itb=0&idpp=insfeed"
  },
  {
    "text": "",
    "url": "https://www.bing.com/images?FORM=SBIRDI#CA!Like"
  },
  {
    "text": "",
    "url": "https://www.bing.com/images?FORM=SBIRDI#CA!Unlike"
  },
  {
    "text": "",
    "url": "https://www.bing.com/images?FORM=SBIRDI#CA!dtmnu"
  },
  {
    "text": "",
    "url": "https://www.bing.com/images/search?view=detailV2&ccid=Ng%2fJm0xf&id=FED6440517D873FC3BDB70D59CA7FABCFD782DF7&thid=OIP.Ng_Jm0xfuWVicYDgTs3h6AAAAA&mediaurl=https%3a%2f%2fi.ytimg.com%2fvi%2f_fQnAAAlAhM%2foardefault.jpg%3fsqp%3d-oaymwEkCJUDENAFSFqQAgHyq4qpAxMIARUAAAAAJQAAyEI9AICiQ3gB%26rs%3dAOn4CLCI_fOOrz2Iu8rIqK87XOUu_2Q7Mw&exph=720&expw=405&FORM=IRPFED&ck=8EDCB0D67D8FA1EA2EE010B783E8ED12&reqid=884BD56324234530B8388CCCFF048294&selectedIndex=1&itb=0&idpp=insfeed"
  },
  {
    "text": "youtube.com",
    "url": "https://www.youtube.com/shorts/_fQnAAAlAhM"
  },
  {
    "text": "",
    "url": "https://www.bing.com/images/search?view=detailV2&ccid=Ng%2fJm0xf&id=FED6440517D873FC3BDB70D59CA7FABCFD782DF7&thid=OIP.Ng_Jm0xfuWVicYDgTs3h6AAAAA&mediaurl=https%3a%2f%2fi.ytimg.com%2fvi%2f_fQnAAAlAhM%2foardefault.jpg%3fsqp%3d-oaymwEkCJUDENAFSFqQAgHyq4qpAxMIARUAAAAAJQAAyEI9AICiQ3gB%26rs%3dAOn4CLCI_fOOrz2Iu8rIqK87XOUu_2Q7Mw&exph=720&expw=405&FORM=IRPFED&ck=8EDCB0D67D8FA1EA2EE010B783E8ED12&reqid=884BD56324234530B8388CCCFF048294&selectedIndex=1&itb=0&idpp=insfeed"
  },
  {
    "text": "If you want some exclusive CAR Collection Then you have to See this one😉💁‍♀️😍  #shorts #viralvideo - YouTube",
    "url": "https://www.bing.com/images/search?view=detailV2&ccid=Ng%2fJm0xf&id=FED6440517D873FC3BDB70D59CA7FABCFD782DF7&thid=OIP.Ng_Jm0xfuWVicYDgTs3h6AAAAA&mediaurl=https%3a%2f%2fi.ytimg.com%2fvi%2f_fQnAAAlAhM%2foardefault.jpg%3fsqp%3d-oaymwEkCJUDENAFSFqQAgHyq4qpAxMIARUAAAAAJQAAyEI9AICiQ3gB%26rs%3dAOn4CLCI_fOOrz2Iu8rIqK87XOUu_2Q7Mw&exph=720&expw=405&FORM=IRPFED&ck=8EDCB0D67D8FA1EA2EE010B783E8ED12&reqid=884BD56324234530B8388CCCFF048294&selectedIndex=1&itb=0&idpp=insfeed"
  },
  {
    "text": "",
    "url": "https://www.bing.com/images?FORM=SBIRDI#CA!Like"
  },
  {
    "text": "",
    "url": "https://www.bing.com/images?FORM=SBIRDI#CA!Unlike"
  },
  {
    "text": "",
    "url": "https://www.bing.com/images?FORM=SBIRDI#CA!dtmnu"
  },
  {
    "text": "",
    "url": "https://www.bing.com/images/search?view=detailV2&ccid=UiGy3rZ0&id=24A95EE4414F17C9806D675899BD8682A3CAA433&thid=OIP.UiGy3rZ0-MB_9kIsY0-8FwHaEz&mediaurl=https%3a%2f%2fp4.wallpaperbetter.com%2fwallpaper%2f770%2f797%2f100%2ftrees-night-lights-river-wallpaper-preview.jpg&exph=472&expw=728&FORM=IRPFED&ck=A8170A6F6A4315A56D883A606389FB0B&reqid=884BD56324234530B8388CCCFF048294&selectedIndex=5&itb=0&idpp=insfeed"
  },
  {
    "text": "wallpaperbetter.com",
    "url": "https://www.wallpaperbetter.com/en/hd-wallpaper-axxma"
  },
  {
    "text": "",
    "url": "https://www.bing.com/images/search?view=detailV2&ccid=UiGy3rZ0&id=24A95EE4414F17C9806D675899BD8682A3CAA433&thid=OIP.UiGy3rZ0-MB_9kIsY0-8FwHaEz&mediaurl=https%3a%2f%2fp4.wallpaperbetter.com%2fwallpaper%2f770%2f797%2f100%2ftrees-night-lights-river-wallpaper-preview.jpg&exph=472&expw=728&FORM=IRPFED&ck=A8170A6F6A4315A56D883A606389FB0B&reqid=884BD56324234530B8388CCCFF048294&selectedIndex=5&itb=0&idpp=insfeed"
  },
  {
    "text": "Trees, night, lights, river, home, China, Hunan Province, HD wallpaper | Wallpaperbetter",
    "url": "https://www.bing.com/images/search?view=detailV2&ccid=UiGy3rZ0&id=24A95EE4414F17C9806D675899BD8682A3CAA433&thid=OIP.UiGy3rZ0-MB_9kIsY0-8FwHaEz&mediaurl=https%3a%2f%2fp4.wallpaperbetter.com%2fwallpaper%2f770%2f797%2f100%2ftrees-night-lights-river-wallpaper-preview.jpg&exph=472&expw=728&FORM=IRPFED&ck=A8170A6F6A4315A56D883A606389FB0B&reqid=884BD56324234530B8388CCCFF048294&selectedIndex=5&itb=0&idpp=insfeed"
  },
  {
    "text": "",
    "url": "https://www.bing.com/images?FORM=SBIRDI#CA!Like"
  },
  {
    "text": "",
    "url": "https://www.bing.com/images?FORM=SBIRDI#CA!Unlike"
  },
  {
    "text": "",
    "url": "https://www.bing.com/images?FORM=SBIRDI#CA!dtmnu"
  },
  {
    "text": "",
    "url": "https://www.bing.com/images/search?view=detailV2&ccid=uSGsHfh7&id=CF46AC8A55ED48E6C4749DCC734949B9F553E779&thid=OIP.uSGsHfh7ucxX63a0YfBorAHaOB&mediaurl=https%3a%2f%2fi.pinimg.com%2f736x%2fd5%2f42%2f19%2fd54219565e535229fb3342f1fe6cf4b3.jpg&exph=909&expw=480&FORM=IRPFED&ck=0F8DD71187555DFBB8B765C00D6A0450&reqid=884BD56324234530B8388CCCFF048294&selectedIndex=6&itb=0&idpp=insfeed"
  },
  {
    "text": "bodrumwasukur.github.io",
    "url": "https://bodrumwasukur.github.io/post/aesthetic-greek-god-wallpaper/"
  },
  {
    "text": "",
    "url": "https://www.bing.com/images/search?view=detailV2&ccid=uSGsHfh7&id=CF46AC8A55ED48E6C4749DCC734949B9F553E779&thid=OIP.uSGsHfh7ucxX63a0YfBorAHaOB&mediaurl=https%3a%2f%2fi.pinimg.com%2f736x%2fd5%2f42%2f19%2fd54219565e535229fb3342f1fe6cf4b3.jpg&exph=909&expw=480&FORM=IRPFED&ck=0F8DD71187555DFBB8B765C00D6A0450&reqid=884BD56324234530B8388CCCFF048294&selectedIndex=6&itb=0&idpp=insfeed"
  },
  {
    "text": "Aesthetic Greek God Wallpaper - Loki &amp; Sylvie Lock Screen In 2021 | Bodrumwasukur",
    "url": "https://www.bing.com/images/search?view=detailV2&ccid=uSGsHfh7&id=CF46AC8A55ED48E6C4749DCC734949B9F553E779&thid=OIP.uSGsHfh7ucxX63a0YfBorAHaOB&mediaurl=https%3a%2f%2fi.pinimg.com%2f736x%2fd5%2f42%2f19%2fd54219565e535229fb3342f1fe6cf4b3.jpg&exph=909&expw=480&FORM=IRPFED&ck=0F8DD71187555DFBB8B765C00D6A0450&reqid=884BD56324234530B8388CCCFF048294&selectedIndex=6&itb=0&idpp=insfeed"
  },
  {
    "text": "",
    "url": "https://www.bing.com/images?FORM=SBIRDI#CA!Like"
  },
  {
    "text": "",
    "url": "https://www.bing.com/images?FORM=SBIRDI#CA!Unlike"
  },
  {
    "text": "",
    "url": "https://www.bing.com/images?FORM=SBIRDI#CA!dtmnu"
  },
  {
    "text": "",
    "url": "https://www.bing.com/images/search?view=detailV2&ccid=iL2PO%2fg6&id=0F2829A89BD3633798495367860E70855A519C90&thid=OIP.iL2PO_g6bnd0aAVH5EnulwAAAA&mediaurl=https%3a%2f%2fi.ytimg.com%2fvi%2fd7I5B6TjyYo%2foardefault.jpg%3fsqp%3d-oaymwEkCJUDENAFSFqQAgHyq4qpAxMIARUAAAAAJQAAyEI9AICiQ3gB%26rs%3dAOn4CLBOZ6iURNP8DkhyXCyodUxSj-T1zQ&exph=720&expw=405&FORM=IRPFED&ck=FDDD6F3ED13A0EDBC9B07F5E0873BB6D&reqid=884BD56324234530B8388CCCFF048294&selectedIndex=10&itb=0&idpp=insfeed"
  },
  {
    "text": "youtube.com",
    "url": "https://www.youtube.com/shorts/d7I5B6TjyYo"
  },
  {
    "text": "",
    "url": "https://www.bing.com/images/search?view=detailV2&ccid=iL2PO%2fg6&id=0F2829A89BD3633798495367860E70855A519C90&thid=OIP.iL2PO_g6bnd0aAVH5EnulwAAAA&mediaurl=https%3a%2f%2fi.ytimg.com%2fvi%2fd7I5B6TjyYo%2foardefault.jpg%3fsqp%3d-oaymwEkCJUDENAFSFqQAgHyq4qpAxMIARUAAAAAJQAAyEI9AICiQ3gB%26rs%3dAOn4CLBOZ6iURNP8DkhyXCyodUxSj-T1zQ&exph=720&expw=405&FORM=IRPFED&ck=FDDD6F3ED13A0EDBC9B07F5E0873BB6D&reqid=884BD56324234530B8388CCCFF048294&selectedIndex=10&itb=0&idpp=insfeed"
  },
  {
    "text": "McLaren P1 in Pubg🤫 #shorts - YouTube",
    "url": "https://www.bing.com/images/search?view=detailV2&ccid=iL2PO%2fg6&id=0F2829A89BD3633798495367860E70855A519C90&thid=OIP.iL2PO_g6bnd0aAVH5EnulwAAAA&mediaurl=https%3a%2f%2fi.ytimg.com%2fvi%2fd7I5B6TjyYo%2foardefault.jpg%3fsqp%3d-oaymwEkCJUDENAFSFqQAgHyq4qpAxMIARUAAAAAJQAAyEI9AICiQ3gB%26rs%3dAOn4CLBOZ6iURNP8DkhyXCyodUxSj-T1zQ&exph=720&expw=405&FORM=IRPFED&ck=FDDD6F3ED13A0EDBC9B07F5E0873BB6D&reqid=884BD56324234530B8388CCCFF048294&selectedIndex=10&itb=0&idpp=insfeed"
  },
  {
    "text": "",
    "url": "https://www.bing.com/images?FORM=SBIRDI#CA!Like"
  },
  {
    "text": "",
    "url": "https://www.bing.com/images?FORM=SBIRDI#CA!Unlike"
  },
  {
    "text": "",
    "url": "https://www.bing.com/images?FORM=SBIRDI#CA!dtmnu"
  },
  {
    "text": "",
    "url": "https://www.bing.com/images/search?view=detailV2&ccid=PUbSLBT9&id=C41DB037BC29488A9105B1EACFF8D4BE40B68567&thid=OIP.PUbSLBT91ESFwZRjsOPePQHaKm&mediaurl=https%3a%2f%2fi.pinimg.com%2foriginals%2f5d%2f4c%2f08%2f5d4c085760ff0d3b1ade9eadb7ddd4b4.jpg&exph=960&expw=671&FORM=IRPFED&ck=02FCC3B9D15E37CED2CA1B62372C9E96&reqid=884BD56324234530B8388CCCFF048294&selectedIndex=14&itb=0&idpp=insfeed"
  },
  {
    "text": "artofit.org",
    "url": "https://www.artofit.org/image-gallery/933371091498126989/dreamy-landscapes-at-night-inspired-by-space-stars-and-video-games/"
  },
  {
    "text": "",
    "url": "https://www.bing.com/images/search?view=detailV2&ccid=PUbSLBT9&id=C41DB037BC29488A9105B1EACFF8D4BE40B68567&thid=OIP.PUbSLBT91ESFwZRjsOPePQHaKm&mediaurl=https%3a%2f%2fi.pinimg.com%2foriginals%2f5d%2f4c%2f08%2f5d4c085760ff0d3b1ade9eadb7ddd4b4.jpg&exph=960&expw=671&FORM=IRPFED&ck=02FCC3B9D15E37CED2CA1B62372C9E96&reqid=884BD56324234530B8388CCCFF048294&selectedIndex=14&itb=0&idpp=insfeed"
  },
  {
    "text": "Dreamy landscapes at night inspired by space stars and video games – Artofit",
    "url": "https://www.bing.com/images/search?view=detailV2&ccid=PUbSLBT9&id=C41DB037BC29488A9105B1EACFF8D4BE40B68567&thid=OIP.PUbSLBT91ESFwZRjsOPePQHaKm&mediaurl=https%3a%2f%2fi.pinimg.com%2foriginals%2f5d%2f4c%2f08%2f5d4c085760ff0d3b1ade9eadb7ddd4b4.jpg&exph=960&expw=671&FORM=IRPFED&ck=02FCC3B9D15E37CED2CA1B62372C9E96&reqid=884BD56324234530B8388CCCFF048294&selectedIndex=14&itb=0&idpp=insfeed"
  },
  {
    "text": "",
    "url": "https://www.bing.com/images?FORM=SBIRDI#CA!Like"
  },
  {
    "text": "",
    "url": "https://www.bing.com/images?FORM=SBIRDI#CA!Unlike"
  },
  {
    "text": "",
    "url": "https://www.bing.com/images?FORM=SBIRDI#CA!dtmnu"
  },
  {
    "text": "",
    "url": "https://www.bing.com/images/search?view=detailV2&ccid=plrgOP2D&id=5718CE28950DA69CCEC22738A3D3D5A47051FC07&thid=OIP.plrgOP2DoDAWtnmdMOu56AHaKd&mediaurl=https%3a%2f%2fi.pinimg.com%2foriginals%2f33%2fbc%2ff7%2f33bcf789908a9a6bd821e2386e575917.jpg&exph=1200&expw=850&FORM=IRPFED&ck=E473A2A2FCC4FF46EFFCA5AA71525F6F&reqid=884BD56324234530B8388CCCFF048294&selectedIndex=17&itb=0&idpp=insfeed"
  },
  {
    "text": "artofit.org",
    "url": "https://www.artofit.org/image-gallery/652670171012295224/witchy-aesthetic/"
  },
  {
    "text": "",
    "url": "https://www.bing.com/images/search?view=detailV2&ccid=plrgOP2D&id=5718CE28950DA69CCEC22738A3D3D5A47051FC07&thid=OIP.plrgOP2DoDAWtnmdMOu56AHaKd&mediaurl=https%3a%2f%2fi.pinimg.com%2foriginals%2f33%2fbc%2ff7%2f33bcf789908a9a6bd821e2386e575917.jpg&exph=1200&expw=850&FORM=IRPFED&ck=E473A2A2FCC4FF46EFFCA5AA71525F6F&reqid=884BD56324234530B8388CCCFF048294&selectedIndex=17&itb=0&idpp=insfeed"
  },
  {
    "text": "Witchy aesthetic – Artofit",
    "url": "https://www.bing.com/images/search?view=detailV2&ccid=plrgOP2D&id=5718CE28950DA69CCEC22738A3D3D5A47051FC07&thid=OIP.plrgOP2DoDAWtnmdMOu56AHaKd&mediaurl=https%3a%2f%2fi.pinimg.com%2foriginals%2f33%2fbc%2ff7%2f33bcf789908a9a6bd821e2386e575917.jpg&exph=1200&expw=850&FORM=IRPFED&ck=E473A2A2FCC4FF46EFFCA5AA71525F6F&reqid=884BD56324234530B8388CCCFF048294&selectedIndex=17&itb=0&idpp=insfeed"
  },
  {
    "text": "",
    "url": "https://www.bing.com/images?FORM=SBIRDI#CA!Like"
  },
  {
    "text": "",
    "url": "https://www.bing.com/images?FORM=SBIRDI#CA!Unlike"
  },
  {
    "text": "",
    "url": "https://www.bing.com/images?FORM=SBIRDI#CA!dtmnu"
  },
  {
    "text": "",
    "url": "https://www.bing.com/images/search?view=detailV2&ccid=Rv8dzxDG&id=0A76D8FAA4A362B11E5E600FC57BDB168D8CF762&thid=OIP.Rv8dzxDGMxmUefFxyPNijQHaJF&mediaurl=https%3a%2f%2fcdn11.bigcommerce.com%2fs-fduu8evurl%2fimages%2fstencil%2f1280w%2fuploaded_images%2fblue.jpg%3ft%3d1593485603&exph=1570&expw=1280&FORM=IRPFED&ck=8DDB2059EB1D80F8E46394D9CECE943B&reqid=884BD56324234530B8388CCCFF048294&selectedIndex=20&itb=0&idpp=insfeed"
  },
  {
    "text": "gatorkennels.com",
    "url": "https://www.gatorkennels.com/blog/breed-spotlight-the-french-bulldog/"
  },
  {
    "text": "",
    "url": "https://www.bing.com/images/search?view=detailV2&ccid=Rv8dzxDG&id=0A76D8FAA4A362B11E5E600FC57BDB168D8CF762&thid=OIP.Rv8dzxDGMxmUefFxyPNijQHaJF&mediaurl=https%3a%2f%2fcdn11.bigcommerce.com%2fs-fduu8evurl%2fimages%2fstencil%2f1280w%2fuploaded_images%2fblue.jpg%3ft%3d1593485603&exph=1570&expw=1280&FORM=IRPFED&ck=8DDB2059EB1D80F8E46394D9CECE943B&reqid=884BD56324234530B8388CCCFF048294&selectedIndex=20&itb=0&idpp=insfeed"
  },
  {
    "text": "Breed Spotlight: The French Bulldog - Gator Kennels",
    "url": "https://www.bing.com/images/search?view=detailV2&ccid=Rv8dzxDG&id=0A76D8FAA4A362B11E5E600FC57BDB168D8CF762&thid=OIP.Rv8dzxDGMxmUefFxyPNijQHaJF&mediaurl=https%3a%2f%2fcdn11.bigcommerce.com%2fs-fduu8evurl%2fimages%2fstencil%2f1280w%2fuploaded_images%2fblue.jpg%3ft%3d1593485603&exph=1570&expw=1280&FORM=IRPFED&ck=8DDB2059EB1D80F8E46394D9CECE943B&reqid=884BD56324234530B8388CCCFF048294&selectedIndex=20&itb=0&idpp=insfeed"
  },
  {
    "text": "",
    "url": "https://www.bing.com/images?FORM=SBIRDI#CA!Like"
  },
  {
    "text": "",
    "url": "https://www.bing.com/images?FORM=SBIRDI#CA!Unlike"
  },
  {
    "text": "",
    "url": "https://www.bing.com/images?FORM=SBIRDI#CA!dtmnu"
  },
  {
    "text": "",
    "url": "https://www.bing.com/images/search?view=detailV2&ccid=nSCsh%2bVI&id=D13F6F184B5C12E40A865516280DB05BC4C550CF&thid=OIP.nSCsh-VIijXoARIG4ykvTAHaKT&mediaurl=https%3a%2f%2fi.pinimg.com%2foriginals%2f13%2f95%2f8a%2f13958a1ef2d1c52482ec0eadb4005f83.jpg&exph=1699&expw=1221&FORM=IRPFED&ck=5B0087D7B8F1B65DCC7F729128B13837&reqid=884BD56324234530B8388CCCFF048294&selectedIndex=22&itb=0&idpp=insfeed"
  },
  {
    "text": "artofit.org",
    "url": "https://www.artofit.org/image-gallery/ancient-egyptian-pharaoh/"
  },
  {
    "text": "",
    "url": "https://www.bing.com/images/search?view=detailV2&ccid=nSCsh%2bVI&id=D13F6F184B5C12E40A865516280DB05BC4C550CF&thid=OIP.nSCsh-VIijXoARIG4ykvTAHaKT&mediaurl=https%3a%2f%2fi.pinimg.com%2foriginals%2f13%2f95%2f8a%2f13958a1ef2d1c52482ec0eadb4005f83.jpg&exph=1699&expw=1221&FORM=IRPFED&ck=5B0087D7B8F1B65DCC7F729128B13837&reqid=884BD56324234530B8388CCCFF048294&selectedIndex=22&itb=0&idpp=insfeed"
  },
  {
    "text": "Ancient egyptian pharaoh – Artofit",
    "url": "https://www.bing.com/images/search?view=detailV2&ccid=nSCsh%2bVI&id=D13F6F184B5C12E40A865516280DB05BC4C550CF&thid=OIP.nSCsh-VIijXoARIG4ykvTAHaKT&mediaurl=https%3a%2f%2fi.pinimg.com%2foriginals%2f13%2f95%2f8a%2f13958a1ef2d1c52482ec0eadb4005f83.jpg&exph=1699&expw=1221&FORM=IRPFED&ck=5B0087D7B8F1B65DCC7F729128B13837&reqid=884BD56324234530B8388CCCFF048294&selectedIndex=22&itb=0&idpp=insfeed"
  },
  {
    "text": "",
    "url": "https://www.bing.com/images?FORM=SBIRDI#CA!Like"
  },
  {
    "text": "",
    "url": "https://www.bing.com/images?FORM=SBIRDI#CA!Unlike"
  },
  {
    "text": "",
    "url": "https://www.bing.com/images?FORM=SBIRDI#CA!dtmnu"
  },
  {
    "text": "",
    "url": "https://www.bing.com/images/search?view=detailV2&ccid=F7C1cycz&id=CDB9C49E494479F0EF7DCC2304173F201B63FE5B&thid=OIP.F7C1cycz8lp7b0E2jtuL1QHaKX&mediaurl=https%3a%2f%2fpreview.redd.it%2fffpf4zi6g9e41.jpg%3fauto%3dwebp%26s%3d6ea309e242c0430b64b79d5b948eb38726defb2b&exph=1909&expw=1363&FORM=IRPFED&ck=40BCA0D1BC6F23D50D4AE73E35EA80D1&reqid=884BD56324234530B8388CCCFF048294&selectedIndex=25&itb=0&idpp=insfeed"
  },
  {
    "text": "reddit.com",
    "url": "https://www.reddit.com/r/oddlysatisfying/comments/ex2c4e/the_way_the_rays_pass_through_this_lush_forest_in/"
  },
  {
    "text": "",
    "url": "https://www.bing.com/images/search?view=detailV2&ccid=F7C1cycz&id=CDB9C49E494479F0EF7DCC2304173F201B63FE5B&thid=OIP.F7C1cycz8lp7b0E2jtuL1QHaKX&mediaurl=https%3a%2f%2fpreview.redd.it%2fffpf4zi6g9e41.jpg%3fauto%3dwebp%26s%3d6ea309e242c0430b64b79d5b948eb38726defb2b&exph=1909&expw=1363&FORM=IRPFED&ck=40BCA0D1BC6F23D50D4AE73E35EA80D1&reqid=884BD56324234530B8388CCCFF048294&selectedIndex=25&itb=0&idpp=insfeed"
  },
  {
    "text": "The way the rays pass through this lush forest in Netherlands! : r/oddlysatisfying",
    "url": "https://www.bing.com/images/search?view=detailV2&ccid=F7C1cycz&id=CDB9C49E494479F0EF7DCC2304173F201B63FE5B&thid=OIP.F7C1cycz8lp7b0E2jtuL1QHaKX&mediaurl=https%3a%2f%2fpreview.redd.it%2fffpf4zi6g9e41.jpg%3fauto%3dwebp%26s%3d6ea309e242c0430b64b79d5b948eb38726defb2b&exph=1909&expw=1363&FORM=IRPFED&ck=40BCA0D1BC6F23D50D4AE73E35EA80D1&reqid=884BD56324234530B8388CCCFF048294&selectedIndex=25&itb=0&idpp=insfeed"
  },
  {
    "text": "",
    "url": "https://www.bing.com/images?FORM=SBIRDI#CA!Like"
  },
  {
    "text": "",
    "url": "https://www.bing.com/images?FORM=SBIRDI#CA!Unlike"
  },
  {
    "text": "",
    "url": "https://www.bing.com/images?FORM=SBIRDI#CA!dtmnu"
  },
  {
    "text": "",
    "url": "https://www.bing.com/images/search?view=detailV2&ccid=PJZYq4Ky&id=E20E2369BC8E58BD024C2786CD175AECFB2FDD1F&thid=OIP.PJZYq4Ky8v2hMe9ndNvzXQHaLH&mediaurl=https%3a%2f%2fblogger.googleusercontent.com%2fimg%2fb%2fR29vZ2xl%2fAVvXsEjBxw9XhldhvuSRhMsE-Y1yQRf40siXigxFuWLQkzANXY4nYgN35VYjCczEr0Bu5DYXS3pAJfi8hibFXBVBdKySxOh6UcEI-bwvxEJF0WHacKz3BkpsKbX6JtmMGCU8b5AVUKT8yfDvx6Gd%2fs1600%2fFRASES.jpg&exph=1200&expw=800&FORM=IRPFED&ck=7C52D69883497750E1A67D268F651E19&reqid=884BD56324234530B8388CCCFF048294&selectedIndex=27&itb=0&idpp=insfeed"
  },
  {
    "text": "misimagenesparatublog.blogspot.com",
    "url": "https://misimagenesparatublog.blogspot.com/"
  },
  {
    "text": "",
    "url": "https://www.bing.com/images/search?view=detailV2&ccid=PJZYq4Ky&id=E20E2369BC8E58BD024C2786CD175AECFB2FDD1F&thid=OIP.PJZYq4Ky8v2hMe9ndNvzXQHaLH&mediaurl=https%3a%2f%2fblogger.googleusercontent.com%2fimg%2fb%2fR29vZ2xl%2fAVvXsEjBxw9XhldhvuSRhMsE-Y1yQRf40siXigxFuWLQkzANXY4nYgN35VYjCczEr0Bu5DYXS3pAJfi8hibFXBVBdKySxOh6UcEI-bwvxEJF0WHacKz3BkpsKbX6JtmMGCU8b5AVUKT8yfDvx6Gd%2fs1600%2fFRASES.jpg&exph=1200&expw=800&FORM=IRPFED&ck=7C52D69883497750E1A67D268F651E19&reqid=884BD56324234530B8388CCCFF048294&selectedIndex=27&itb=0&idpp=insfeed"
  },
  {
    "text": "Beautiful colorful pictures and Gifs",
    "url": "https://www.bing.com/images/search?view=detailV2&ccid=PJZYq4Ky&id=E20E2369BC8E58BD024C2786CD175AECFB2FDD1F&thid=OIP.PJZYq4Ky8v2hMe9ndNvzXQHaLH&mediaurl=https%3a%2f%2fblogger.googleusercontent.com%2fimg%2fb%2fR29vZ2xl%2fAVvXsEjBxw9XhldhvuSRhMsE-Y1yQRf40siXigxFuWLQkzANXY4nYgN35VYjCczEr0Bu5DYXS3pAJfi8hibFXBVBdKySxOh6UcEI-bwvxEJF0WHacKz3BkpsKbX6JtmMGCU8b5AVUKT8yfDvx6Gd%2fs1600%2fFRASES.jpg&exph=1200&expw=800&FORM=IRPFED&ck=7C52D69883497750E1A67D268F651E19&reqid=884BD56324234530B8388CCCFF048294&selectedIndex=27&itb=0&idpp=insfeed"
  },
  {
    "text": "",
    "url": "https://www.bing.com/images?FORM=SBIRDI#CA!Like"
  },
  {
    "text": "",
    "url": "https://www.bing.com/images?FORM=SBIRDI#CA!Unlike"
  },
  {
    "text": "",
    "url": "https://www.bing.com/images?FORM=SBIRDI#CA!dtmnu"
  },
  {
    "text": "",
    "url": "https://www.bing.com/images/search?view=detailV2&ccid=Yxn8GwlP&id=544B87008FC68A04C08581F621E212C159D1F38C&thid=OIP.Yxn8GwlP_3CUp3vu7n98ZQHaJQ&mediaurl=https%3a%2f%2fs3-media0.fl.yelpcdn.com%2fbphoto%2fYNzWn8XDJXNOzEY7zgzt_w%2fo.jpg&exph=800&expw=640&FORM=IRPFED&ck=9CD644ACC3A9B4E5707DB96ED7C1347E&reqid=884BD56324234530B8388CCCFF048294&selectedIndex=30&itb=0&idpp=insfeed"
  },
  {
    "text": "yelp.com",
    "url": "https://www.yelp.com/biz/cimmaron-station-arco"
  },
  {
    "text": "",
    "url": "https://www.bing.com/images/search?view=detailV2&ccid=Yxn8GwlP&id=544B87008FC68A04C08581F621E212C159D1F38C&thid=OIP.Yxn8GwlP_3CUp3vu7n98ZQHaJQ&mediaurl=https%3a%2f%2fs3-media0.fl.yelpcdn.com%2fbphoto%2fYNzWn8XDJXNOzEY7zgzt_w%2fo.jpg&exph=800&expw=640&FORM=IRPFED&ck=9CD644ACC3A9B4E5707DB96ED7C1347E&reqid=884BD56324234530B8388CCCFF048294&selectedIndex=30&itb=0&idpp=insfeed"
  },
  {
    "text": "CIMMARON STATION - Updated December 2024 - Request Information - 632 Butte Ave, Arco, Idaho - Apartments - Phone Num…",
    "url": "https://www.bing.com/images/search?view=detailV2&ccid=Yxn8GwlP&id=544B87008FC68A04C08581F621E212C159D1F38C&thid=OIP.Yxn8GwlP_3CUp3vu7n98ZQHaJQ&mediaurl=https%3a%2f%2fs3-media0.fl.yelpcdn.com%2fbphoto%2fYNzWn8XDJXNOzEY7zgzt_w%2fo.jpg&exph=800&expw=640&FORM=IRPFED&ck=9CD644ACC3A9B4E5707DB96ED7C1347E&reqid=884BD56324234530B8388CCCFF048294&selectedIndex=30&itb=0&idpp=insfeed"
  },
  {
    "text": "",
    "url": "https://www.bing.com/images?FORM=SBIRDI#CA!Like"
  },
  {
    "text": "",
    "url": "https://www.bing.com/images?FORM=SBIRDI#CA!Unlike"
  },
  {
    "text": "",
    "url": "https://www.bing.com/images?FORM=SBIRDI#CA!dtmnu"
  },
  {
    "text": "",
    "url": "https://www.bing.com/images/search?view=detailV2&ccid=mc3%2f%2f4AD&id=75B9DFF4F8370F7A8E5DC2AF8EF7F716AC911EA2&thid=OIP.mc3__4ADsBaT9CqLk5BnngHaNJ&mediaurl=https%3a%2f%2flookaside.instagram.com%2fseo%2fgoogle_widget%2fcrawler%2f%3fmedia_id%3d3590798289407412942&exph=1136&expw=640&FORM=IRPFED&ck=E1016A3EEE5B4FCAE6AD530B3F85C7E4&reqid=884BD56324234530B8388CCCFF048294&selectedIndex=33&itb=0&idpp=insfeed"
  },
  {
    "text": "instagram.com",
    "url": "https://www.instagram.com/faithful._nature/"
  },
  {
    "text": "",
    "url": "https://www.bing.com/images/search?view=detailV2&ccid=mc3%2f%2f4AD&id=75B9DFF4F8370F7A8E5DC2AF8EF7F716AC911EA2&thid=OIP.mc3__4ADsBaT9CqLk5BnngHaNJ&mediaurl=https%3a%2f%2flookaside.instagram.com%2fseo%2fgoogle_widget%2fcrawler%2f%3fmedia_id%3d3590798289407412942&exph=1136&expw=640&FORM=IRPFED&ck=E1016A3EEE5B4FCAE6AD530B3F85C7E4&reqid=884BD56324234530B8388CCCFF048294&selectedIndex=33&itb=0&idpp=insfeed"
  },
  {
    "text": "Faithful._nature (@faithful._nature) • Instagram photos and videos",
    "url": "https://www.bing.com/images/search?view=detailV2&ccid=mc3%2f%2f4AD&id=75B9DFF4F8370F7A8E5DC2AF8EF7F716AC911EA2&thid=OIP.mc3__4ADsBaT9CqLk5BnngHaNJ&mediaurl=https%3a%2f%2flookaside.instagram.com%2fseo%2fgoogle_widget%2fcrawler%2f%3fmedia_id%3d3590798289407412942&exph=1136&expw=640&FORM=IRPFED&ck=E1016A3EEE5B4FCAE6AD530B3F85C7E4&reqid=884BD56324234530B8388CCCFF048294&selectedIndex=33&itb=0&idpp=insfeed"
  },
  {
    "text": "",
    "url": "https://www.bing.com/images?FORM=SBIRDI#CA!Like"
  },
  {
    "text": "",
    "url": "https://www.bing.com/images?FORM=SBIRDI#CA!Unlike"
  },
  {
    "text": "",
    "url": "https://www.bing.com/images?FORM=SBIRDI#CA!dtmnu"
  },
  {
    "text": "",
    "url": "https://www.bing.com/images/search?view=detailV2&ccid=CLpUaQ80&id=2BC7F8E742FEABE73A9B521B9539B03494486B34&thid=OIP.CLpUaQ80hG7_dv3WtkjiwwHaLH&mediaurl=https%3a%2f%2follielythe.com%2fwp-content%2fuploads%2f2017%2f10%2fport-11-img-5.jpg&exph=1200&expw=800&FORM=IRPFED&ck=A2342A0064EA1F9E41A996915014818C&reqid=884BD56324234530B8388CCCFF048294&selectedIndex=2&itb=0&idpp=insfeed"
  },
  {
    "text": "ollielythe.com",
    "url": "https://ollielythe.com/"
  },
  {
    "text": "",
    "url": "https://www.bing.com/images/search?view=detailV2&ccid=CLpUaQ80&id=2BC7F8E742FEABE73A9B521B9539B03494486B34&thid=OIP.CLpUaQ80hG7_dv3WtkjiwwHaLH&mediaurl=https%3a%2f%2follielythe.com%2fwp-content%2fuploads%2f2017%2f10%2fport-11-img-5.jpg&exph=1200&expw=800&FORM=IRPFED&ck=A2342A0064EA1F9E41A996915014818C&reqid=884BD56324234530B8388CCCFF048294&selectedIndex=2&itb=0&idpp=insfeed"
  },
  {
    "text": "Ollie Lythe – Photographer",
    "url": "https://www.bing.com/images/search?view=detailV2&ccid=CLpUaQ80&id=2BC7F8E742FEABE73A9B521B9539B03494486B34&thid=OIP.CLpUaQ80hG7_dv3WtkjiwwHaLH&mediaurl=https%3a%2f%2follielythe.com%2fwp-content%2fuploads%2f2017%2f10%2fport-11-img-5.jpg&exph=1200&expw=800&FORM=IRPFED&ck=A2342A0064EA1F9E41A996915014818C&reqid=884BD56324234530B8388CCCFF048294&selectedIndex=2&itb=0&idpp=insfeed"
  },
  {
    "text": "",
    "url": "https://www.bing.com/images?FORM=SBIRDI#CA!Like"
  },
  {
    "text": "",
    "url": "https://www.bing.com/images?FORM=SBIRDI#CA!Unlike"
  },
  {
    "text": "",
    "url": "https://www.bing.com/images?FORM=SBIRDI#CA!dtmnu"
  },
  {
    "text": "",
    "url": "https://www.bing.com/images/search?view=detailV2&ccid=rvxbD4Cv&id=F0CDD8F93DD15E417EBEA31EDFB8D50BA87CF08B&thid=OIP.rvxbD4CvCHMVsGgRrC5NTAAAAA&mediaurl=http%3a%2f%2fshift.is%2fwp-content%2fuploads%2f2013%2f09%2ftumblr_mp6i37dHzv1s2akbko1_500.jpg&exph=600&expw=429&FORM=IRPFED&ck=A89F170295D17DBAC570B95402E09816&reqid=884BD56324234530B8388CCCFF048294&selectedIndex=4&itb=0&idpp=insfeed"
  },
  {
    "text": "shift.is",
    "url": "https://www.shift.is/thich-nhat-hanh-on-what-a-real-miracle-is/"
  },
  {
    "text": "",
    "url": "https://www.bing.com/images/search?view=detailV2&ccid=rvxbD4Cv&id=F0CDD8F93DD15E417EBEA31EDFB8D50BA87CF08B&thid=OIP.rvxbD4CvCHMVsGgRrC5NTAAAAA&mediaurl=http%3a%2f%2fshift.is%2fwp-content%2fuploads%2f2013%2f09%2ftumblr_mp6i37dHzv1s2akbko1_500.jpg&exph=600&expw=429&FORM=IRPFED&ck=A89F170295D17DBAC570B95402E09816&reqid=884BD56324234530B8388CCCFF048294&selectedIndex=4&itb=0&idpp=insfeed"
  },
  {
    "text": "Thich Nhat Hanh on What a Real Miracle Is – SHIFT",
    "url": "https://www.bing.com/images/search?view=detailV2&ccid=rvxbD4Cv&id=F0CDD8F93DD15E417EBEA31EDFB8D50BA87CF08B&thid=OIP.rvxbD4CvCHMVsGgRrC5NTAAAAA&mediaurl=http%3a%2f%2fshift.is%2fwp-content%2fuploads%2f2013%2f09%2ftumblr_mp6i37dHzv1s2akbko1_500.jpg&exph=600&expw=429&FORM=IRPFED&ck=A89F170295D17DBAC570B95402E09816&reqid=884BD56324234530B8388CCCFF048294&selectedIndex=4&itb=0&idpp=insfeed"
  },
  {
    "text": "",
    "url": "https://www.bing.com/images?FORM=SBIRDI#CA!Like"
  },
  {
    "text": "",
    "url": "https://www.bing.com/images?FORM=SBIRDI#CA!Unlike"
  },
  {
    "text": "",
    "url": "https://www.bing.com/images?FORM=SBIRDI#CA!dtmnu"
  },
  {
    "text": "",
    "url": "https://www.bing.com/images/search?view=detailV2&ccid=YG1yZs1R&id=2721D82426C620F6820E202E7967675864A7CCEC&thid=OIP.YG1yZs1R2e05vQit-Xlp3wHaM9&mediaurl=https%3a%2f%2f64.media.tumblr.com%2f89a19692f72d1cf4437b477c59ef576f%2f75b55078cc3cd3e9-74%2fs1280x1920%2fbe4c3bccafd26f8796cbcc910061455394b48c95.jpg&exph=1200&expw=686&FORM=IRPFED&ck=2D52A9D3AD413870CD24CB3505FB9532&reqid=884BD56324234530B8388CCCFF048294&selectedIndex=7&itb=0&idpp=insfeed"
  },
  {
    "text": "tumblr.com",
    "url": "https://www.tumblr.com/gervanofreire1968"
  },
  {
    "text": "",
    "url": "https://www.bing.com/images/search?view=detailV2&ccid=YG1yZs1R&id=2721D82426C620F6820E202E7967675864A7CCEC&thid=OIP.YG1yZs1R2e05vQit-Xlp3wHaM9&mediaurl=https%3a%2f%2f64.media.tumblr.com%2f89a19692f72d1cf4437b477c59ef576f%2f75b55078cc3cd3e9-74%2fs1280x1920%2fbe4c3bccafd26f8796cbcc910061455394b48c95.jpg&exph=1200&expw=686&FORM=IRPFED&ck=2D52A9D3AD413870CD24CB3505FB9532&reqid=884BD56324234530B8388CCCFF048294&selectedIndex=7&itb=0&idpp=insfeed"
  },
  {
    "text": "@gervanofreire1968 on Tumblr",
    "url": "https://www.bing.com/images/search?view=detailV2&ccid=YG1yZs1R&id=2721D82426C620F6820E202E7967675864A7CCEC&thid=OIP.YG1yZs1R2e05vQit-Xlp3wHaM9&mediaurl=https%3a%2f%2f64.media.tumblr.com%2f89a19692f72d1cf4437b477c59ef576f%2f75b55078cc3cd3e9-74%2fs1280x1920%2fbe4c3bccafd26f8796cbcc910061455394b48c95.jpg&exph=1200&expw=686&FORM=IRPFED&ck=2D52A9D3AD413870CD24CB3505FB9532&reqid=884BD56324234530B8388CCCFF048294&selectedIndex=7&itb=0&idpp=insfeed"
  },
  {
    "text": "",
    "url": "https://www.bing.com/images?FORM=SBIRDI#CA!Like"
  },
  {
    "text": "",
    "url": "https://www.bing.com/images?FORM=SBIRDI#CA!Unlike"
  },
  {
    "text": "",
    "url": "https://www.bing.com/images?FORM=SBIRDI#CA!dtmnu"
  },
  {
    "text": "",
    "url": "https://www.bing.com/images/search?view=detailV2&ccid=0luq0aHi&id=87EEDB580C01EB9DF64993F8B4CB60B7DA234746&thid=OIP.0luq0aHisXTeq809BJNN1gHaHa&mediaurl=https%3a%2f%2fwww.horseandman.com%2fwp-content%2fuploads%2f2023%2f10%2f386558836_890968205718891_5853983295004344322_n.jpeg&exph=640&expw=640&FORM=IRPFED&ck=4597B12A7B2D6294D43B24E19966F5A0&reqid=884BD56324234530B8388CCCFF048294&selectedIndex=11&itb=0&idpp=insfeed"
  },
  {
    "text": "horseandman.com",
    "url": "https://www.horseandman.com/saturday-phoblog/saturday-is-phoblog-day-366/10/06/2023/"
  },
  {
    "text": "",
    "url": "https://www.bing.com/images/search?view=detailV2&ccid=0luq0aHi&id=87EEDB580C01EB9DF64993F8B4CB60B7DA234746&thid=OIP.0luq0aHisXTeq809BJNN1gHaHa&mediaurl=https%3a%2f%2fwww.horseandman.com%2fwp-content%2fuploads%2f2023%2f10%2f386558836_890968205718891_5853983295004344322_n.jpeg&exph=640&expw=640&FORM=IRPFED&ck=4597B12A7B2D6294D43B24E19966F5A0&reqid=884BD56324234530B8388CCCFF048294&selectedIndex=11&itb=0&idpp=insfeed"
  },
  {
    "text": "SATURDAY IS PHOBLOG DAY! - Horse and Man",
    "url": "https://www.bing.com/images/search?view=detailV2&ccid=0luq0aHi&id=87EEDB580C01EB9DF64993F8B4CB60B7DA234746&thid=OIP.0luq0aHisXTeq809BJNN1gHaHa&mediaurl=https%3a%2f%2fwww.horseandman.com%2fwp-content%2fuploads%2f2023%2f10%2f386558836_890968205718891_5853983295004344322_n.jpeg&exph=640&expw=640&FORM=IRPFED&ck=4597B12A7B2D6294D43B24E19966F5A0&reqid=884BD56324234530B8388CCCFF048294&selectedIndex=11&itb=0&idpp=insfeed"
  },
  {
    "text": "",
    "url": "https://www.bing.com/images?FORM=SBIRDI#CA!Like"
  },
  {
    "text": "",
    "url": "https://www.bing.com/images?FORM=SBIRDI#CA!Unlike"
  },
  {
    "text": "",
    "url": "https://www.bing.com/images?FORM=SBIRDI#CA!dtmnu"
  },
  {
    "text": "",
    "url": "https://www.bing.com/images/search?view=detailV2&ccid=GsTnvfr5&id=0265188EB0D5A1FA076EBEFFAA63415D0B37A5B1&thid=OIP.GsTnvfr5RJ6f3YcNedoQtgAAAA&mediaurl=https%3a%2f%2fi.pinimg.com%2foriginals%2fac%2fa7%2f0f%2faca70f7dc09acc0c1d7638239afb9681.jpg&exph=626&expw=417&FORM=IRPFED&ck=6D4B44048FF0B960FC457FE90AD68BED&reqid=884BD56324234530B8388CCCFF048294&selectedIndex=12&itb=0&idpp=insfeed"
  },
  {
    "text": "artofit.org",
    "url": "https://www.artofit.org/image-gallery/1069042030271871142/art-reference-woman-lighting/"
  },
  {
    "text": "",
    "url": "https://www.bing.com/images/search?view=detailV2&ccid=GsTnvfr5&id=0265188EB0D5A1FA076EBEFFAA63415D0B37A5B1&thid=OIP.GsTnvfr5RJ6f3YcNedoQtgAAAA&mediaurl=https%3a%2f%2fi.pinimg.com%2foriginals%2fac%2fa7%2f0f%2faca70f7dc09acc0c1d7638239afb9681.jpg&exph=626&expw=417&FORM=IRPFED&ck=6D4B44048FF0B960FC457FE90AD68BED&reqid=884BD56324234530B8388CCCFF048294&selectedIndex=12&itb=0&idpp=insfeed"
  },
  {
    "text": "Art reference woman lighting – Artofit",
    "url": "https://www.bing.com/images/search?view=detailV2&ccid=GsTnvfr5&id=0265188EB0D5A1FA076EBEFFAA63415D0B37A5B1&thid=OIP.GsTnvfr5RJ6f3YcNedoQtgAAAA&mediaurl=https%3a%2f%2fi.pinimg.com%2foriginals%2fac%2fa7%2f0f%2faca70f7dc09acc0c1d7638239afb9681.jpg&exph=626&expw=417&FORM=IRPFED&ck=6D4B44048FF0B960FC457FE90AD68BED&reqid=884BD56324234530B8388CCCFF048294&selectedIndex=12&itb=0&idpp=insfeed"
  },
  {
    "text": "",
    "url": "https://www.bing.com/images?FORM=SBIRDI#CA!Like"
  },
  {
    "text": "",
    "url": "https://www.bing.com/images?FORM=SBIRDI#CA!Unlike"
  },
  {
    "text": "",
    "url": "https://www.bing.com/images?FORM=SBIRDI#CA!dtmnu"
  },
  {
    "text": "",
    "url": "https://www.bing.com/images/search?view=detailV2&ccid=wueSZW3U&id=62030DB375338D2866AF40AA820E618202576EAC&thid=OIP.wueSZW3UH-Y53uo4TXRZ7gHaJZ&mediaurl=http%3a%2f%2fdownwardscausation.com%2fwp-content%2fuploads%2f2015%2f12%2fLD01.jpg&exph=800&expw=630&FORM=IRPFED&ck=5E65A2BE5AC52EF672D0489F9D3A5FAD&reqid=884BD56324234530B8388CCCFF048294&selectedIndex=15&itb=0&idpp=insfeed"
  },
  {
    "text": "downwardscausation.com",
    "url": "http://downwardscausation.com/tag/laurence-demaison/"
  },
  {
    "text": "",
    "url": "https://www.bing.com/images/search?view=detailV2&ccid=wueSZW3U&id=62030DB375338D2866AF40AA820E618202576EAC&thid=OIP.wueSZW3UH-Y53uo4TXRZ7gHaJZ&mediaurl=http%3a%2f%2fdownwardscausation.com%2fwp-content%2fuploads%2f2015%2f12%2fLD01.jpg&exph=800&expw=630&FORM=IRPFED&ck=5E65A2BE5AC52EF672D0489F9D3A5FAD&reqid=884BD56324234530B8388CCCFF048294&selectedIndex=15&itb=0&idpp=insfeed"
  },
  {
    "text": "laurence demaison – DOWNWARDS CAUSATION",
    "url": "https://www.bing.com/images/search?view=detailV2&ccid=wueSZW3U&id=62030DB375338D2866AF40AA820E618202576EAC&thid=OIP.wueSZW3UH-Y53uo4TXRZ7gHaJZ&mediaurl=http%3a%2f%2fdownwardscausation.com%2fwp-content%2fuploads%2f2015%2f12%2fLD01.jpg&exph=800&expw=630&FORM=IRPFED&ck=5E65A2BE5AC52EF672D0489F9D3A5FAD&reqid=884BD56324234530B8388CCCFF048294&selectedIndex=15&itb=0&idpp=insfeed"
  },
  {
    "text": "",
    "url": "https://www.bing.com/images?FORM=SBIRDI#CA!Like"
  },
  {
    "text": "",
    "url": "https://www.bing.com/images?FORM=SBIRDI#CA!Unlike"
  },
  {
    "text": "",
    "url": "https://www.bing.com/images?FORM=SBIRDI#CA!dtmnu"
  },
  {
    "text": "",
    "url": "https://www.bing.com/images/search?view=detailV2&ccid=trvp5BuI&id=A7F934E17668BC6AE9BA3CB1760EF328FF9E2221&thid=OIP.trvp5BuIflpT4IcUEfr0SgHaJ9&mediaurl=https%3a%2f%2fi.mdel.net%2foftheminute%2fimages%2f2017%2f08%2fMDC_OLIVERTWIST3820_2-1012x1362.jpg&exph=1362&expw=1012&FORM=IRPFED&ck=B6FE01164E7B95796959DD22DC0BC7C3&reqid=884BD56324234530B8388CCCFF048294&selectedIndex=18&itb=0&idpp=insfeed"
  },
  {
    "text": "models.com",
    "url": "https://models.com/oftheminute/?p=96664"
  },
  {
    "text": "",
    "url": "https://www.bing.com/images/search?view=detailV2&ccid=trvp5BuI&id=A7F934E17668BC6AE9BA3CB1760EF328FF9E2221&thid=OIP.trvp5BuIflpT4IcUEfr0SgHaJ9&mediaurl=https%3a%2f%2fi.mdel.net%2foftheminute%2fimages%2f2017%2f08%2fMDC_OLIVERTWIST3820_2-1012x1362.jpg&exph=1362&expw=1012&FORM=IRPFED&ck=B6FE01164E7B95796959DD22DC0BC7C3&reqid=884BD56324234530B8388CCCFF048294&selectedIndex=18&itb=0&idpp=insfeed"
  },
  {
    "text": "Beauty Twist – Of The Minute",
    "url": "https://www.bing.com/images/search?view=detailV2&ccid=trvp5BuI&id=A7F934E17668BC6AE9BA3CB1760EF328FF9E2221&thid=OIP.trvp5BuIflpT4IcUEfr0SgHaJ9&mediaurl=https%3a%2f%2fi.mdel.net%2foftheminute%2fimages%2f2017%2f08%2fMDC_OLIVERTWIST3820_2-1012x1362.jpg&exph=1362&expw=1012&FORM=IRPFED&ck=B6FE01164E7B95796959DD22DC0BC7C3&reqid=884BD56324234530B8388CCCFF048294&selectedIndex=18&itb=0&idpp=insfeed"
  },
  {
    "text": "",
    "url": "https://www.bing.com/images?FORM=SBIRDI#CA!Like"
  },
  {
    "text": "",
    "url": "https://www.bing.com/images?FORM=SBIRDI#CA!Unlike"
  },
  {
    "text": "",
    "url": "https://www.bing.com/images?FORM=SBIRDI#CA!dtmnu"
  },
  {
    "text": "",
    "url": "https://www.bing.com/images/search?view=detailV2&ccid=U6hVKqtj&id=FE05AA898EEF15A3592306EC5FEBDF7963426FD7&thid=OIP.U6hVKqtjUiZEZBkEzRF0dgHaLH&mediaurl=https%3a%2f%2f64.media.tumblr.com%2fc600cba3ac5fbb341365c08fad3e5ce5%2f534cab1cb763a4af-ca%2fs640x960%2f0dc409df63b34818b3981aeb8a0cda2c18e9a2b1.jpg&exph=960&expw=640&FORM=IRPFED&ck=1DC62B6379CC1472C518AFBF1446BBDD&reqid=884BD56324234530B8388CCCFF048294&selectedIndex=21&itb=0&idpp=insfeed"
  },
  {
    "text": "tumblr.com",
    "url": "https://www.tumblr.com/deerlakebobsstuff"
  },
  {
    "text": "",
    "url": "https://www.bing.com/images/search?view=detailV2&ccid=U6hVKqtj&id=FE05AA898EEF15A3592306EC5FEBDF7963426FD7&thid=OIP.U6hVKqtjUiZEZBkEzRF0dgHaLH&mediaurl=https%3a%2f%2f64.media.tumblr.com%2fc600cba3ac5fbb341365c08fad3e5ce5%2f534cab1cb763a4af-ca%2fs640x960%2f0dc409df63b34818b3981aeb8a0cda2c18e9a2b1.jpg&exph=960&expw=640&FORM=IRPFED&ck=1DC62B6379CC1472C518AFBF1446BBDD&reqid=884BD56324234530B8388CCCFF048294&selectedIndex=21&itb=0&idpp=insfeed"
  },
  {
    "text": "@deerlakebobsstuff on Tumblr",
    "url": "https://www.bing.com/images/search?view=detailV2&ccid=U6hVKqtj&id=FE05AA898EEF15A3592306EC5FEBDF7963426FD7&thid=OIP.U6hVKqtjUiZEZBkEzRF0dgHaLH&mediaurl=https%3a%2f%2f64.media.tumblr.com%2fc600cba3ac5fbb341365c08fad3e5ce5%2f534cab1cb763a4af-ca%2fs640x960%2f0dc409df63b34818b3981aeb8a0cda2c18e9a2b1.jpg&exph=960&expw=640&FORM=IRPFED&ck=1DC62B6379CC1472C518AFBF1446BBDD&reqid=884BD56324234530B8388CCCFF048294&selectedIndex=21&itb=0&idpp=insfeed"
  },
  {
    "text": "",
    "url": "https://www.bing.com/images?FORM=SBIRDI#CA!Like"
  },
  {
    "text": "",
    "url": "https://www.bing.com/images?FORM=SBIRDI#CA!Unlike"
  },
  {
    "text": "",
    "url": "https://www.bing.com/images?FORM=SBIRDI#CA!dtmnu"
  },
  {
    "text": "",
    "url": "https://www.bing.com/images/search?view=detailV2&ccid=QbMTvtWF&id=100F34D49D5FA4838D3CD6538EC5BBCD00AE7D99&thid=OIP.QbMTvtWFF4Q6Lsr-5NlznQAAAA&mediaurl=https%3a%2f%2fi.ytimg.com%2fvi%2f_OGQlePIFOE%2foar2.jpg%3fsqp%3d-oaymwEkCJUDENAFSFqQAgHyq4qpAxMIARUAAAAAJQAAyEI9AICiQ3gB%26rs%3dAOn4CLCw0lYZucpaa7VhYZL88irBt5-yLw&exph=720&expw=405&FORM=IRPFED&ck=3B6650B7CDB8E2DAC8C531A9EACA1D37&reqid=884BD56324234530B8388CCCFF048294&selectedIndex=24&itb=0&idpp=insfeed"
  },
  {
    "text": "youtube.com",
    "url": "https://www.youtube.com/shorts/_OGQlePIFOE"
  },
  {
    "text": "",
    "url": "https://www.bing.com/images/search?view=detailV2&ccid=QbMTvtWF&id=100F34D49D5FA4838D3CD6538EC5BBCD00AE7D99&thid=OIP.QbMTvtWFF4Q6Lsr-5NlznQAAAA&mediaurl=https%3a%2f%2fi.ytimg.com%2fvi%2f_OGQlePIFOE%2foar2.jpg%3fsqp%3d-oaymwEkCJUDENAFSFqQAgHyq4qpAxMIARUAAAAAJQAAyEI9AICiQ3gB%26rs%3dAOn4CLCw0lYZucpaa7VhYZL88irBt5-yLw&exph=720&expw=405&FORM=IRPFED&ck=3B6650B7CDB8E2DAC8C531A9EACA1D37&reqid=884BD56324234530B8388CCCFF048294&selectedIndex=24&itb=0&idpp=insfeed"
  },
  {
    "text": "#supercarlovers #car # #supercarsbuzz #carlover #shorts #video #speed #400 #sorts #reels #car #viral - YouTube",
    "url": "https://www.bing.com/images/search?view=detailV2&ccid=QbMTvtWF&id=100F34D49D5FA4838D3CD6538EC5BBCD00AE7D99&thid=OIP.QbMTvtWFF4Q6Lsr-5NlznQAAAA&mediaurl=https%3a%2f%2fi.ytimg.com%2fvi%2f_OGQlePIFOE%2foar2.jpg%3fsqp%3d-oaymwEkCJUDENAFSFqQAgHyq4qpAxMIARUAAAAAJQAAyEI9AICiQ3gB%26rs%3dAOn4CLCw0lYZucpaa7VhYZL88irBt5-yLw&exph=720&expw=405&FORM=IRPFED&ck=3B6650B7CDB8E2DAC8C531A9EACA1D37&reqid=884BD56324234530B8388CCCFF048294&selectedIndex=24&itb=0&idpp=insfeed"
  },
  {
    "text": "",
    "url": "https://www.bing.com/images?FORM=SBIRDI#CA!Like"
  },
  {
    "text": "",
    "url": "https://www.bing.com/images?FORM=SBIRDI#CA!Unlike"
  },
  {
    "text": "",
    "url": "https://www.bing.com/images?FORM=SBIRDI#CA!dtmnu"
  },
  {
    "text": "",
    "url": "https://www.bing.com/images/search?view=detailV2&ccid=8I%2bqP%2b5S&id=A839AB1C2167DAC38CC8DD5374E6B5AF613885E5&thid=OIP.8I-qP-5SblhsDR2v2sG_pAHaMW&mediaurl=https%3a%2f%2fi.pinimg.com%2foriginals%2feb%2fd7%2f93%2febd793443e08055042fb88ce8717eefc.jpg&exph=1800&expw=1080&FORM=IRPFED&ck=26B3801B49A5B1435BCBEFE3A6AFDAE0&reqid=884BD56324234530B8388CCCFF048294&selectedIndex=28&itb=0&idpp=insfeed"
  },
  {
    "text": "artofit.org",
    "url": "https://www.artofit.org/image-gallery/397090892147777629/it-s-a-beautiful-world-фото/"
  },
  {
    "text": "",
    "url": "https://www.bing.com/images/search?view=detailV2&ccid=8I%2bqP%2b5S&id=A839AB1C2167DAC38CC8DD5374E6B5AF613885E5&thid=OIP.8I-qP-5SblhsDR2v2sG_pAHaMW&mediaurl=https%3a%2f%2fi.pinimg.com%2foriginals%2feb%2fd7%2f93%2febd793443e08055042fb88ce8717eefc.jpg&exph=1800&expw=1080&FORM=IRPFED&ck=26B3801B49A5B1435BCBEFE3A6AFDAE0&reqid=884BD56324234530B8388CCCFF048294&selectedIndex=28&itb=0&idpp=insfeed"
  },
  {
    "text": "It s a beautiful world фото – Artofit",
    "url": "https://www.bing.com/images/search?view=detailV2&ccid=8I%2bqP%2b5S&id=A839AB1C2167DAC38CC8DD5374E6B5AF613885E5&thid=OIP.8I-qP-5SblhsDR2v2sG_pAHaMW&mediaurl=https%3a%2f%2fi.pinimg.com%2foriginals%2feb%2fd7%2f93%2febd793443e08055042fb88ce8717eefc.jpg&exph=1800&expw=1080&FORM=IRPFED&ck=26B3801B49A5B1435BCBEFE3A6AFDAE0&reqid=884BD56324234530B8388CCCFF048294&selectedIndex=28&itb=0&idpp=insfeed"
  },
  {
    "text": "",
    "url": "https://www.bing.com/images?FORM=SBIRDI#CA!Like"
  },
  {
    "text": "",
    "url": "https://www.bing.com/images?FORM=SBIRDI#CA!Unlike"
  },
  {
    "text": "",
    "url": "https://www.bing.com/images?FORM=SBIRDI#CA!dtmnu"
  },
  {
    "text": "",
    "url": "https://www.bing.com/images/search?view=detailV2&ccid=nw7GomEx&id=BC3BB0A12405FBD64DB4A32DC58DA436EDB2F1AE&thid=OIP.nw7GomEx9H0sQtKitw2zqQHaJ3&mediaurl=https%3a%2f%2fi.pinimg.com%2foriginals%2f19%2f00%2fc7%2f1900c7f66679959e09cd67cb4ea6ba31.jpg&exph=981&expw=736&FORM=IRPFED&ck=4D3B3C7A99A740A741B85C349592A424&reqid=884BD56324234530B8388CCCFF048294&selectedIndex=31&itb=0&idpp=insfeed"
  },
  {
    "text": "artofit.org",
    "url": "https://www.artofit.org/image-gallery/121949102402159906/springvibes/"
  },
  {
    "text": "",
    "url": "https://www.bing.com/images/search?view=detailV2&ccid=nw7GomEx&id=BC3BB0A12405FBD64DB4A32DC58DA436EDB2F1AE&thid=OIP.nw7GomEx9H0sQtKitw2zqQHaJ3&mediaurl=https%3a%2f%2fi.pinimg.com%2foriginals%2f19%2f00%2fc7%2f1900c7f66679959e09cd67cb4ea6ba31.jpg&exph=981&expw=736&FORM=IRPFED&ck=4D3B3C7A99A740A741B85C349592A424&reqid=884BD56324234530B8388CCCFF048294&selectedIndex=31&itb=0&idpp=insfeed"
  },
  {
    "text": "Springvibes – Artofit",
    "url": "https://www.bing.com/images/search?view=detailV2&ccid=nw7GomEx&id=BC3BB0A12405FBD64DB4A32DC58DA436EDB2F1AE&thid=OIP.nw7GomEx9H0sQtKitw2zqQHaJ3&mediaurl=https%3a%2f%2fi.pinimg.com%2foriginals%2f19%2f00%2fc7%2f1900c7f66679959e09cd67cb4ea6ba31.jpg&exph=981&expw=736&FORM=IRPFED&ck=4D3B3C7A99A740A741B85C349592A424&reqid=884BD56324234530B8388CCCFF048294&selectedIndex=31&itb=0&idpp=insfeed"
  },
  {
    "text": "",
    "url": "https://www.bing.com/images?FORM=SBIRDI#CA!Like"
  },
  {
    "text": "",
    "url": "https://www.bing.com/images?FORM=SBIRDI#CA!Unlike"
  },
  {
    "text": "",
    "url": "https://www.bing.com/images?FORM=SBIRDI#CA!dtmnu"
  },
  {
    "text": "",
    "url": "https://www.bing.com/images/search?view=detailV2&ccid=AX0iVngR&id=7AD359509F5D153BA1708005581C93642AB8CBFB&thid=OIP.AX0iVngR52Efoep8Ma8gcgHaNs&mediaurl=https%3a%2f%2flookaside.fbsbx.com%2flookaside%2fcrawler%2fmedia%2f%3fmedia_id%3d268841537021557&exph=1043&expw=564&FORM=IRPFED&ck=4D41697DBBC1AECD03C816B6B69C8720&reqid=884BD56324234530B8388CCCFF048294&selectedIndex=34&itb=0&idpp=insfeed"
  },
  {
    "text": "facebook.com",
    "url": "https://www.facebook.com/SpacemomentsCom/posts/the-2040-mercedes-benz-w196r-streamliner-concept-pays-tribute-to-the-original-w1/268842350354809/"
  },
  {
    "text": "",
    "url": "https://www.bing.com/images/search?view=detailV2&ccid=AX0iVngR&id=7AD359509F5D153BA1708005581C93642AB8CBFB&thid=OIP.AX0iVngR52Efoep8Ma8gcgHaNs&mediaurl=https%3a%2f%2flookaside.fbsbx.com%2flookaside%2fcrawler%2fmedia%2f%3fmedia_id%3d268841537021557&exph=1043&expw=564&FORM=IRPFED&ck=4D41697DBBC1AECD03C816B6B69C8720&reqid=884BD56324234530B8388CCCFF048294&selectedIndex=34&itb=0&idpp=insfeed"
  },
  {
    "text": "The 2040 Mercedes-Benz W196R... - Spacemoments.com",
    "url": "https://www.bing.com/images/search?view=detailV2&ccid=AX0iVngR&id=7AD359509F5D153BA1708005581C93642AB8CBFB&thid=OIP.AX0iVngR52Efoep8Ma8gcgHaNs&mediaurl=https%3a%2f%2flookaside.fbsbx.com%2flookaside%2fcrawler%2fmedia%2f%3fmedia_id%3d268841537021557&exph=1043&expw=564&FORM=IRPFED&ck=4D41697DBBC1AECD03C816B6B69C8720&reqid=884BD56324234530B8388CCCFF048294&selectedIndex=34&itb=0&idpp=insfeed"
  },
  {
    "text": "",
    "url": "https://www.bing.com/images?FORM=SBIRDI#CA!Like"
  },
  {
    "text": "",
    "url": "https://www.bing.com/images?FORM=SBIRDI#CA!Unlike"
  },
  {
    "text": "",
    "url": "https://www.bing.com/images?FORM=SBIRDI#CA!dtmnu"
  },
  {
    "text": "",
    "url": "https://www.bing.com/images?FORM=SBIRDI"
  },
  {
    "text": "",
    "url": "https://www.bing.com/images?FORM=SBIRDI"
  },
  {
    "text": "Show less like this",
    "url": "https://www.bing.com/images?FORM=SBIRDI#CA!Dislike"
  },
  {
    "text": "Report content",
    "url": "https://www.bing.com/images?FORM=SBIRDI#CA!Report"
  },
  {
    "text": "",
    "url": "https://www.bing.com/images?FORM=SBIRDI#CA!CloseDislike"
  },
  {
    "text": "Refresh",
    "url": "https://www.bing.com/images?FORM=SBIRDI#CA!fdrefresh"
  },
  {
    "text": "Undo",
    "url": "https://www.bing.com/images?FORM=SBIRDI#CA!UndoDislike"
  },
  {
    "text": "Privacy",
    "url": "http://go.microsoft.com/fwlink/?LinkId=521839"
  },
  {
    "text": "Terms",
    "url": "http://go.microsoft.com/fwlink/?LinkID=246338"
  },
  {
    "text": "Advertise",
    "url": "https://go.microsoft.com/fwlink/?linkid=868922"
  },
  {
    "text": "About our ads",
    "url": "http://go.microsoft.com/fwlink/?LinkID=286759"
  },
  {
    "text": "Help",
    "url": "https://support.microsoft.com/topic/82d20721-2d6f-4012-a13d-d1910ccf203f"
  },
  {
    "text": "Feedback",
    "url": "https://www.bing.com/images?FORM=SBIRDI"
  },
  {
    "text": "Consumer Health Privacy",
    "url": "https://go.microsoft.com/fwlink/?linkid=2259814"
  }
]